censor_this/__init__.py
censor_this/data.json
censor_this/main.py
censor_this-0.1.2.dist-info/entry_points.txt
censor_this-0.1.2.dist-info/LICENSE
censor_this-0.1.2.dist-info/WHEEL
censor_this-0.1.2.dist-info/METADATA
censor_this-0.1.2.dist-info/RECORD
