Metadata-Version: 2.1
Name: censor-this
Version: 0.1.2
Summary: A command line tool to censor words in an image.
Author: Colbe Roberson
Author-email: cgr28@njit.edu
Requires-Python: >=3.8,<4.0
Classifier: Programming Language :: Python :: 3
Classifier: Programming Language :: Python :: 3.8
Classifier: Programming Language :: Python :: 3.9
Classifier: Programming Language :: Python :: 3.10
Requires-Dist: opencv-python (>=4.6.0.66,<5.0.0.0)
Requires-Dist: pytesseract (>=0.3.10,<0.4.0)
Requires-Dist: typer[all] (>=0.6.1,<0.7.0)
